<?xml version="1.0" encoding="UTF-8"?> 
<?xml-stylesheet type="text/xsl" href="./xsl/sorted_table.xsl" ?> 
<students> 
    <student> 
        <name>Ritvik Gupta</name> 
        <reg>19CBE0397</reg> 
        <college>VIT</college> 
        <branch>CSE</branch> 
        <course>IWP</course> 
        <year-of-join>2019</year-of-join> 
        <email>laks@abc.com</email> 
        <cgpa>8.3</cgpa> 
        <num-courses>6</num-courses> 
        <num-credits>20</num-credits> 
    </student> 
    <student> 
        <name>Akhil</name> 
        <reg>12345</reg> 
        <college>MNO College</college> 
        <branch>CSE</branch> 
        <course>IWP</course> 
        <year-of-join>2019</year-of-join> 
        <email>akhil@gmail.com</email> 
        <cgpa>8.9</cgpa> 
        <num-courses>8</num-courses> 
        <num-credits>26</num-credits> 
    </student> 
    <student> 
        <name>Dan</name> 
        <reg>19bce0138</reg> 
        <college>Delhi Univ</college> 
        <branch>CSE</branch> 
        <course>IWP</course> 
        <year-of-join>2019</year-of-join> 
        <email>dan@gmail.com</email> 
        <cgpa>8.2</cgpa> 
        <num-courses>7</num-courses> 
        <num-credits>23</num-credits> 
    </student> 
    <student> 
        <name>Bran</name> 
        <reg>19bce</reg> 
        <college>IIT</college> 
        <branch>CSE</branch> 
        <course>IWP</course> 
        <year-of-join>2019</year-of-join> 
        <email>bran@yahoo.com</email> 
        <cgpa>9</cgpa> 
        <num-courses>7</num-courses> 
        <num-credits>23</num-credits> 
    </student> 
    <student> 
        <name>Erica</name> 
        <reg>20BCE</reg> 
        <college>JP Univ</college> 
        <branch>CSE</branch> 
        <course>IWP</course> 
        <year-of-join>2019</year-of-join> 
        <email>erics@gmail.com</email> 
        <cgpa>6</cgpa> 
        <num-courses>7</num-courses> 
        <num-credits>23</num-credits> 
    </student> 
    <student> 
        <name>Samuel</name> 
        <reg>4567</reg> 
        <college>NIT</college> 
        <branch>CSE</branch> 
        <course>IWP</course> 
        <year-of-join>2019</year-of-join> 
        <email>samuel@hotmail.com</email> 
        <cgpa>8.6</cgpa> 
        <num-courses>7</num-courses> 
        <num-credits>23</num-credits> 
    </student> 
    <student> 
        <name> Sahil</name> 
        <reg>19MCE0110</reg> 
        <college>VIT</college> 
        <branch>CSE</branch> 
        <course>IWP</course> 
        <year-of-join>2019</year-of-join> 
        <email>sah@gmail.com</email> 
        <cgpa>8</cgpa> 
        <num-courses>7</num-courses> 
        <num-credits>23</num-credits> 
    </student> 
    <student> 
        <name>Saurabh</name> 
        <reg>20BCE014</reg> 
        <college>Chandigarh Uni</college> 
        <branch>CSE</branch> 
        <course>IWP</course> 
        <year-of-join>2019</year-of-join> 
        <email>saura@bnmm.com</email> 
        <cgpa>9.2</cgpa> 
        <num-courses>7</num-courses> 
        <num-credits>23</num-credits> 
    </student> 
    <student> 
        <name>Sunil</name> 
        <reg>BJ961</reg> 
        <college>College of Commerce</college> 
        <branch>Banking</branch> 
        <course>IWP</course> 
        <year-of-join>2019</year-of-join> 
        <email>nk@bing.com</email> 
        <cgpa>6.8</cgpa> 
        <num-courses>7</num-courses> 
        <num-credits>23</num-credits> 
    </student> 
    <student> 
        <name>Cam</name> 
        <reg>cam123</reg> 
        <college>ED University</college> 
        <branch>CSE</branch> 
        <course>IWP</course> 
        <year-of-join>2019</year-of-join> 
        <email>camn@abc.com</email> 
        <cgpa>8.4</cgpa> 
        <num-courses>7</num-courses> 
        <num-credits>23</num-credits> 
    </student> 
</students>
